sutras/__init__.py
sutras/cli/__init__.py
sutras/cli/main.py
sutras/core/__init__.py
sutras/core/abi.py
sutras/core/builder.py
sutras/core/config.py
sutras/core/evaluator.py
sutras/core/installer.py
sutras/core/loader.py
sutras/core/lockfile.py
sutras/core/naming.py
sutras/core/publisher.py
sutras/core/registry.py
sutras/core/resolver.py
sutras/core/semver.py
sutras/core/skill.py
sutras/core/test_runner.py
sutras-0.2.0.dist-info/METADATA
sutras-0.2.0.dist-info/WHEEL
sutras-0.2.0.dist-info/entry_points.txt
sutras-0.2.0.dist-info/licenses/LICENSE
sutras-0.2.0.dist-info/RECORD
