Metadata-Version: 2.4
Name: sutras
Version: 0.2.0
Summary: Devtool for creating, testing, and distributing Anthropic Agent Skills with lifecycle management, Skill ABI, and federated registries
Project-URL: Homepage, https://github.com/anistark/sutras
Project-URL: Documentation, https://github.com/anistark/sutras#readme
Project-URL: Repository, https://github.com/anistark/sutras
Author-email: Kumar Anirudha <oss@anirudha.dev>
License: MIT
License-File: LICENSE
Keywords: agent,ai,anthropic,cli,devtools,packaging,registry,skills
Classifier: Development Status :: 3 - Alpha
Classifier: Intended Audience :: Developers
Classifier: License :: OSI Approved :: MIT License
Classifier: Programming Language :: Python :: 3
Classifier: Programming Language :: Python :: 3.11
Classifier: Programming Language :: Python :: 3.12
Classifier: Programming Language :: Python :: 3.13
Classifier: Topic :: Scientific/Engineering :: Artificial Intelligence
Classifier: Topic :: Software Development :: Libraries :: Python Modules
Requires-Python: >=3.11
Requires-Dist: click>=8.0.0
Requires-Dist: jinja2>=3.0.0
Requires-Dist: pydantic>=2.0.0
Requires-Dist: pyyaml>=6.0
Provides-Extra: eval
Requires-Dist: ragas>=0.4.3; extra == 'eval'
